<model>G
    <voxels>F
        <voxel x="-20" y="0" z="0" r="0.749020" g="0.729412" b="0.741176" a="1.000000" />:
        <voxel x="-19" y="0" z="0" r="0.827451" g="0.803922" b="0.815686" a="1.000000" />C
        <voxel x="-18" y="0" z="0" r="0.749020" g="0.729412" b="0.741176" a="1.000000" />,
        <voxel x="-20" y="1" z="0" r="0.749020" g="0.729412" b="0.741176" a="1.000000" />O
        <voxel x="-19" y="1" z="0" r="0.749020" g="0.729412" b="0.741176" a="1.000000" />N
        <voxel x="-18" y="1" z="0" r="0.749020" g="0.729412" b="0.741176" a="1.000000" />L
        <voxel x="-20" y="2" z="0" r="0.749020" g="0.729412" b="0.741176" a="1.000000" />Y
        <voxel x="-19" y="2" z="0" r="0.827451" g="0.803922" b="0.815686" a="1.000000" />G
        <voxel x="-18" y="2" z="0" r="0.749020" g="0.729412" b="0.741176" a="1.000000" />F
        <voxel x="-20" y="3" z="0" r="0.749020" g="0.729412" b="0.741176" a="1.000000" />:
        <voxel x="-19" y="3" z="0" r="0.827451" g="0.803922" b="0.815686" a="1.000000" />C
        <voxel x="-18" y="3" z="0" r="0.749020" g="0.729412" b="0.741176" a="1.000000" />,
        <voxel x="-20" y="0" z="1" r="0.827451" g="0.803922" b="0.815686" a="1.000000" />O
        <voxel x="-19" y="0" z="1" r="0.827451" g="0.803922" b="0.815686" a="1.000000" />N
        <voxel x="-18" y="0" z="1" r="0.827451" g="0.803922" b="0.815686" a="1.000000" />L
        <voxel x="-20" y="1" z="1" r="0.827451" g="0.803922" b="0.815686" a="1.000000" />Y
        <voxel x="-20" y="6" z="4" r="0.282353" g="0.274510" b="0.290196" a="1.000000" />G
        <voxel x="-18" y="1" z="1" r="0.827451" g="0.803922" b="0.815686" a="1.000000" />F
        <voxel x="-20" y="2" z="1" r="0.827451" g="0.803922" b="0.815686" a="1.000000" />:
        <voxel x="-21" y="6" z="4" r="0.282353" g="0.274510" b="0.290196" a="1.000000" />C
        <voxel x="-18" y="2" z="1" r="0.827451" g="0.803922" b="0.815686" a="1.000000" />,
        <voxel x="-20" y="3" z="1" r="0.827451" g="0.803922" b="0.815686" a="1.000000" />O
        <voxel x="-22" y="6" z="4" r="0.282353" g="0.274510" b="0.290196" a="1.000000" />N
        <voxel x="-18" y="3" z="1" r="0.827451" g="0.803922" b="0.815686" a="1.000000" />L
        <voxel x="-23" y="4" z="1" r="0.345098" g="0.341176" b="0.360784" a="1.000000" />Y
        <voxel x="-22" y="4" z="1" r="0.345098" g="0.341176" b="0.360784" a="1.000000" />G
        <voxel x="-21" y="4" z="1" r="0.345098" g="0.341176" b="0.360784" a="1.000000" />F
        <voxel x="-20" y="4" z="1" r="0.768627" g="0.611765" b="0.505882" a="1.000000" />:
        <voxel x="-19" y="4" z="1" r="0.290196" g="0.290196" b="0.290196" a="1.000000" />C
        <voxel x="-18" y="4" z="1" r="0.768627" g="0.611765" b="0.505882" a="1.000000" />,
        <voxel x="-17" y="4" z="1" r="0.345098" g="0.341176" b="0.360784" a="1.000000" />O
        <voxel x="-16" y="4" z="1" r="0.345098" g="0.341176" b="0.360784" a="1.000000" />N
        <voxel x="-15" y="4" z="1" r="0.345098" g="0.341176" b="0.360784" a="1.000000" />L
        <voxel x="-14" y="4" z="1" r="0.345098" g="0.341176" b="0.360784" a="1.000000" />Y
        <voxel x="-13" y="4" z="1" r="0.345098" g="0.341176" b="0.360784" a="1.000000" />G
        <voxel x="-12" y="4" z="1" r="0.345098" g="0.341176" b="0.360784" a="1.000000" />F
        <voxel x="-11" y="4" z="1" r="0.345098" g="0.341176" b="0.360784" a="1.000000" />:
        <voxel x="-10" y="4" z="1" r="0.345098" g="0.341176" b="0.360784" a="1.000000" />C
        <voxel x="-24" y="5" z="1" r="0.345098" g="0.341176" b="0.360784" a="1.000000" />,
        <voxel x="-23" y="5" z="1" r="0.345098" g="0.341176" b="0.360784" a="1.000000" />O
        <voxel x="-20" y="5" z="1" r="0.768627" g="0.611765" b="0.505882" a="1.000000" />N
        <voxel x="-19" y="5" z="1" r="0.290196" g="0.290196" b="0.290196" a="1.000000" />L
        <voxel x="-18" y="5" z="1" r="0.768627" g="0.611765" b="0.505882" a="1.000000" />Y
        <voxel x="-17" y="5" z="1" r="0.321569" g="0.309804" b="0.329412" a="1.000000" />G
        <voxel x="-16" y="5" z="1" r="0.345098" g="0.341176" b="0.360784" a="1.000000" />F
        <voxel x="-15" y="5" z="1" r="0.345098" g="0.341176" b="0.360784" a="1.000000" />:
        <voxel x="-14" y="5" z="1" r="0.345098" g="0.341176" b="0.360784" a="1.000000" />C
        <voxel x="-13" y="5" z="1" r="0.345098" g="0.341176" b="0.360784" a="1.000000" />,
        <voxel x="-12" y="5" z="1" r="0.321569" g="0.309804" b="0.329412" a="1.000000" />O
        <voxel x="-17" y="6" z="1" r="0.345098" g="0.341176" b="0.360784" a="1.000000" />N
        <voxel x="-20" y="0" z="2" r="0.827451" g="0.803922" b="0.815686" a="1.000000" />L
        <voxel x="-19" y="0" z="2" r="0.827451" g="0.803922" b="0.815686" a="1.000000" />Y
        <voxel x="-18" y="0" z="2" r="0.827451" g="0.803922" b="0.815686" a="1.000000" />G
        <voxel x="-20" y="1" z="2" r="0.827451" g="0.803922" b="0.815686" a="1.000000" />F
        <voxel x="-23" y="6" z="4" r="0.282353" g="0.274510" b="0.290196" a="1.000000" />:
        <voxel x="-18" y="1" z="2" r="0.827451" g="0.803922" b="0.815686" a="1.000000" />C
        <voxel x="-12" y="1" z="2" r="0.250980" g="0.235294" b="0.250980" a="1.000000" />,
        <voxel x="-11" y="1" z="2" r="0.250980" g="0.235294" b="0.250980" a="1.000000" />O
        <voxel x="-6" y="1" z="2" r="0.713725" g="0.400000" b="0.356863" a="1.000000" />N
        <voxel x="-3" y="1" z="2" r="0.713725" g="0.400000" b="0.356863" a="1.000000" />L
        <voxel x="-2" y="1" z="2" r="0.713725" g="0.400000" b="0.356863" a="1.000000" />Y
        <voxel x="-1" y="1" z="2" r="0.250980" g="0.235294" b="0.250980" a="1.000000" />G
        <voxel x="-20" y="2" z="2" r="0.827451" g="0.803922" b="0.815686" a="1.000000" />F
        <voxel x="-18" y="3" z="4" r="0.749020" g="0.729412" b="0.741176" a="1.000000" />:
        <voxel x="-18" y="2" z="2" r="0.827451" g="0.803922" b="0.815686" a="1.000000" />C
        <voxel x="-12" y="2" z="2" r="0.250980" g="0.235294" b="0.250980" a="1.000000" />,
        <voxel x="-11" y="2" z="2" r="0.250980" g="0.235294" b="0.250980" a="1.000000" />O
        <voxel x="-7" y="2" z="2" r="0.713725" g="0.400000" b="0.356863" a="1.000000" />N
        <voxel x="-6" y="2" z="2" r="0.713725" g="0.400000" b="0.356863" a="1.000000" />L
        <voxel x="-5" y="2" z="2" r="0.713725" g="0.400000" b="0.356863" a="1.000000" />Y
        <voxel x="-4" y="2" z="2" r="0.713725" g="0.400000" b="0.356863" a="1.000000" />G
        <voxel x="-3" y="2" z="2" r="0.713725" g="0.400000" b="0.356863" a="1.000000" />F
        <voxel x="-2" y="2" z="2" r="0.250980" g="0.235294" b="0.250980" a="1.000000" />:
        <voxel x="-1" y="2" z="2" r="0.250980" g="0.235294" b="0.250980" a="1.000000" />C
        <voxel x="-20" y="3" z="2" r="0.827451" g="0.803922" b="0.815686" a="1.000000" />,
        <voxel x="-19" y="3" z="4" r="0.827451" g="0.803922" b="0.815686" a="1.000000" />O
        <voxel x="-18" y="3" z="2" r="0.827451" g="0.803922" b="0.815686" a="1.000000" />N
        <voxel x="-15" y="3" z="2" r="0.250980" g="0.235294" b="0.250980" a="1.000000" />L
        <voxel x="-13" y="3" z="2" r="0.345098" g="0.341176" b="0.360784" a="1.000000" />Y
        <voxel x="-12" y="3" z="2" r="0.345098" g="0.341176" b="0.360784" a="1.000000" />G
        <voxel x="-8" y="3" z="2" r="0.713725" g="0.400000" b="0.356863" a="1.000000" />F
        <voxel x="-7" y="3" z="2" r="0.713725" g="0.400000" b="0.356863" a="1.000000" />:
        <voxel x="-2" y="3" z="2" r="0.713725" g="0.400000" b="0.356863" a="1.000000" />C
        <voxel x="-1" y="3" z="2" r="0.250980" g="0.235294" b="0.250980" a="1.000000" />,
        <voxel x="-31" y="4" z="2" r="0.286275" g="0.278431" b="0.294118" a="1.000000" />O
        <voxel x="-30" y="4" z="2" r="0.305882" g="0.294118" b="0.313725" a="1.000000" />N
        <voxel x="-29" y="4" z="2" r="0.286275" g="0.278431" b="0.294118" a="1.000000" />L
        <voxel x="-28" y="4" z="2" r="0.345098" g="0.341176" b="0.360784" a="1.000000" />Y
        <voxel x="-27" y="4" z="2" r="0.345098" g="0.341176" b="0.360784" a="1.000000" />G
        <voxel x="-26" y="4" z="2" r="0.345098" g="0.341176" b="0.360784" a="1.000000" />F
        <voxel x="-25" y="4" z="2" r="0.345098" g="0.341176" b="0.360784" a="1.000000" />:
        <voxel x="-24" y="4" z="2" r="0.345098" g="0.341176" b="0.360784" a="1.000000" />C
        <voxel x="-23" y="4" z="2" r="0.345098" g="0.341176" b="0.360784" a="1.000000" />,
        <voxel x="-22" y="4" z="2" r="0.345098" g="0.341176" b="0.360784" a="1.000000" />O
        <voxel x="-21" y="4" z="2" r="0.345098" g="0.341176" b="0.360784" a="1.000000" />N
        <voxel x="-20" y="3" z="4" r="0.749020" g="0.729412" b="0.741176" a="1.000000" />L
        <voxel x="-18" y="2" z="4" r="0.749020" g="0.729412" b="0.741176" a="1.000000" />Y
        <voxel x="-19" y="2" z="4" r="0.827451" g="0.803922" b="0.815686" a="1.000000" />G
        <voxel x="-17" y="4" z="2" r="0.345098" g="0.341176" b="0.360784" a="1.000000" />F
        <voxel x="-16" y="4" z="2" r="0.345098" g="0.341176" b="0.360784" a="1.000000" />:
        <voxel x="-20" y="2" z="4" r="0.749020" g="0.729412" b="0.741176" a="1.000000" />C
        <voxel x="-14" y="4" z="2" r="0.345098" g="0.341176" b="0.360784" a="1.000000" />,
        <voxel x="-18" y="1" z="4" r="0.749020" g="0.729412" b="0.741176" a="1.000000" />O
        <voxel x="-19" y="1" z="4" r="0.749020" g="0.729412" b="0.741176" a="1.000000" />N
        <voxel x="-11" y="4" z="2" r="0.345098" g="0.341176" b="0.360784" a="1.000000" />L
        <voxel x="-10" y="4" z="2" r="0.345098" g="0.341176" b="0.360784" a="1.000000" />Y
        <voxel x="-9" y="4" z="2" r="0.713725" g="0.400000" b="0.356863" a="1.000000" />G
        <voxel x="-8" y="4" z="2" r="0.713725" g="0.400000" b="0.356863" a="1.000000" />F
        <voxel x="-3" y="4" z="2" r="0.713725" g="0.400000" b="0.356863" a="1.000000" />:
        <voxel x="-2" y="4" z="2" r="0.713725" g="0.400000" b="0.356863" a="1.000000" />C
        <voxel x="-1" y="4" z="2" r="0.250980" g="0.235294" b="0.250980" a="1.000000" />,
        <voxel x="-38" y="5" z="2" r="0.282353" g="0.274510" b="0.290196" a="1.000000" />O
        <voxel x="-37" y="5" z="2" r="0.282353" g="0.274510" b="0.290196" a="1.000000" />N
        <voxel x="-36" y="5" z="2" r="0.345098" g="0.341176" b="0.360784" a="1.000000" />L
        <voxel x="-35" y="5" z="2" r="0.345098" g="0.341176" b="0.360784" a="1.000000" />Y
        <voxel x="-34" y="5" z="2" r="0.345098" g="0.341176" b="0.360784" a="1.000000" />G
        <voxel x="-33" y="5" z="2" r="0.345098" g="0.341176" b="0.360784" a="1.000000" />F
        <voxel x="-32" y="5" z="2" r="0.345098" g="0.341176" b="0.360784" a="1.000000" />:
        <voxel x="-31" y="5" z="2" r="0.345098" g="0.341176" b="0.360784" a="1.000000" />C
        <voxel x="-30" y="5" z="2" r="0.345098" g="0.341176" b="0.360784" a="1.000000" />,
        <voxel x="-29" y="5" z="2" r="0.321569" g="0.309804" b="0.329412" a="1.000000" />O
        <voxel x="-28" y="5" z="2" r="0.282353" g="0.274510" b="0.290196" a="1.000000" />N
        <voxel x="-27" y="5" z="2" r="0.282353" g="0.274510" b="0.290196" a="1.000000" />L
        <voxel x="-26" y="5" z="2" r="0.282353" g="0.274510" b="0.290196" a="1.000000" />Y
        <voxel x="-25" y="5" z="2" r="0.282353" g="0.274510" b="0.290196" a="1.000000" />G
        <voxel x="-20" y="1" z="4" r="0.749020" g="0.729412" b="0.741176" a="1.000000" />F
        <voxel x="-23" y="5" z="2" r="0.345098" g="0.341176" b="0.360784" a="1.000000" />:
        <voxel x="-22" y="5" z="2" r="0.321569" g="0.309804" b="0.329412" a="1.000000" />C
        <voxel x="-21" y="5" z="2" r="0.321569" g="0.309804" b="0.329412" a="1.000000" />,
        <voxel x="-18" y="0" z="4" r="0.749020" g="0.729412" b="0.741176" a="1.000000" />O
        <voxel x="-19" y="0" z="4" r="0.827451" g="0.803922" b="0.815686" a="1.000000" />N
        <voxel x="-20" y="0" z="4" r="0.749020" g="0.729412" b="0.741176" a="1.000000" />L
        <voxel x="-17" y="6" z="3" r="0.345098" g="0.341176" b="0.360784" a="1.000000" />Y
        <voxel x="-24" y="6" z="3" r="0.411765" g="0.400000" b="0.427451" a="1.000000" />G
        <voxel x="-12" y="5" z="3" r="0.321569" g="0.309804" b="0.329412" a="1.000000" />F
        <voxel x="-13" y="5" z="3" r="0.345098" g="0.341176" b="0.360784" a="1.000000" />:
        <voxel x="-14" y="5" z="3" r="0.345098" g="0.341176" b="0.360784" a="1.000000" />C
        <voxel x="-15" y="5" z="3" r="0.345098" g="0.341176" b="0.360784" a="1.000000" />,
        <voxel x="-11" y="5" z="2" r="0.345098" g="0.341176" b="0.360784" a="1.000000" />O
        <voxel x="-10" y="5" z="2" r="0.345098" g="0.341176" b="0.360784" a="1.000000" />N
        <voxel x="-9" y="5" z="2" r="0.713725" g="0.400000" b="0.356863" a="1.000000" />L
        <voxel x="-8" y="5" z="2" r="0.713725" g="0.400000" b="0.356863" a="1.000000" />Y
        <voxel x="-7" y="5" z="2" r="0.713725" g="0.400000" b="0.356863" a="1.000000" />G
        <voxel x="-6" y="5" z="2" r="0.713725" g="0.400000" b="0.356863" a="1.000000" />F
        <voxel x="-5" y="5" z="2" r="0.713725" g="0.400000" b="0.356863" a="1.000000" />:
        <voxel x="-4" y="5" z="2" r="0.713725" g="0.400000" b="0.356863" a="1.000000" />C
        <voxel x="-3" y="5" z="2" r="0.713725" g="0.400000" b="0.356863" a="1.000000" />,
        <voxel x="-2" y="5" z="2" r="0.713725" g="0.400000" b="0.356863" a="1.000000" />O
        <voxel x="-1" y="5" z="2" r="0.250980" g="0.235294" b="0.250980" a="1.000000" />N
        <voxel x="-36" y="6" z="2" r="0.282353" g="0.274510" b="0.290196" a="1.000000" />L
        <voxel x="-24" y="6" z="2" r="0.411765" g="0.400000" b="0.427451" a="1.000000" />Y
        <voxel x="-21" y="6" z="2" r="0.345098" g="0.341176" b="0.360784" a="1.000000" />G
        <voxel x="-20" y="6" z="2" r="0.282353" g="0.274510" b="0.290196" a="1.000000" />F
        <voxel x="-19" y="6" z="2" r="0.282353" g="0.274510" b="0.290196" a="1.000000" />:
        <voxel x="-18" y="6" z="2" r="0.282353" g="0.274510" b="0.290196" a="1.000000" />C
        <voxel x="-17" y="6" z="2" r="0.345098" g="0.341176" b="0.360784" a="1.000000" />,
        <voxel x="-16" y="6" z="2" r="0.282353" g="0.274510" b="0.290196" a="1.000000" />O
        <voxel x="-15" y="6" z="2" r="0.282353" g="0.274510" b="0.290196" a="1.000000" />N
        <voxel x="-14" y="6" z="2" r="0.282353" g="0.274510" b="0.290196" a="1.000000" />L
        <voxel x="-13" y="6" z="2" r="0.282353" g="0.274510" b="0.290196" a="1.000000" />Y
        <voxel x="-12" y="6" z="2" r="0.282353" g="0.274510" b="0.290196" a="1.000000" />G
        <voxel x="-11" y="6" z="2" r="0.282353" g="0.274510" b="0.290196" a="1.000000" />F
        <voxel x="-2" y="6" z="2" r="0.250980" g="0.235294" b="0.250980" a="1.000000" />:
        <voxel x="-1" y="6" z="2" r="0.250980" g="0.235294" b="0.250980" a="1.000000" />C
        <voxel x="-15" y="7" z="2" r="0.282353" g="0.274510" b="0.290196" a="1.000000" />,
        <voxel x="-13" y="7" z="2" r="0.282353" g="0.274510" b="0.290196" a="1.000000" />O
        <voxel x="-20" y="0" z="3" r="0.827451" g="0.803922" b="0.815686" a="1.000000" />N
        <voxel x="-19" y="0" z="3" r="0.827451" g="0.803922" b="0.815686" a="1.000000" />L
        <voxel x="-18" y="0" z="3" r="0.827451" g="0.803922" b="0.815686" a="1.000000" />Y
        <voxel x="-20" y="1" z="3" r="0.827451" g="0.803922" b="0.815686" a="1.000000" />G
        <voxel x="-16" y="5" z="3" r="0.345098" g="0.341176" b="0.360784" a="1.000000" />F
        <voxel x="-18" y="1" z="3" r="0.827451" g="0.803922" b="0.815686" a="1.000000" />:
        <voxel x="-20" y="2" z="3" r="0.827451" g="0.803922" b="0.815686" a="1.000000" />C
        <voxel x="-17" y="5" z="3" r="0.321569" g="0.309804" b="0.329412" a="1.000000" />,
        <voxel x="-18" y="2" z="3" r="0.827451" g="0.803922" b="0.815686" a="1.000000" />O
        <voxel x="-20" y="3" z="3" r="0.827451" g="0.803922" b="0.815686" a="1.000000" />N
        <voxel x="-18" y="5" z="3" r="0.768627" g="0.611765" b="0.505882" a="1.000000" />L
        <voxel x="-18" y="3" z="3" r="0.827451" g="0.803922" b="0.815686" a="1.000000" />Y
        <voxel x="-23" y="4" z="3" r="0.345098" g="0.341176" b="0.360784" a="1.000000" />G
        <voxel x="-22" y="4" z="3" r="0.345098" g="0.341176" b="0.360784" a="1.000000" />F
        <voxel x="-21" y="4" z="3" r="0.345098" g="0.341176" b="0.360784" a="1.000000" />:
        <voxel x="-20" y="4" z="3" r="0.768627" g="0.611765" b="0.505882" a="1.000000" />C
        <voxel x="-19" y="4" z="3" r="0.290196" g="0.290196" b="0.290196" a="1.000000" />,
        <voxel x="-18" y="4" z="3" r="0.768627" g="0.611765" b="0.505882" a="1.000000" />O
        <voxel x="-17" y="4" z="3" r="0.345098" g="0.341176" b="0.360784" a="1.000000" />N
        <voxel x="-16" y="4" z="3" r="0.345098" g="0.341176" b="0.360784" a="1.000000" />L
        <voxel x="-15" y="4" z="3" r="0.345098" g="0.341176" b="0.360784" a="1.000000" />Y
        <voxel x="-14" y="4" z="3" r="0.345098" g="0.341176" b="0.360784" a="1.000000" />G
        <voxel x="-13" y="4" z="3" r="0.345098" g="0.341176" b="0.360784" a="1.000000" />F
        <voxel x="-12" y="4" z="3" r="0.345098" g="0.341176" b="0.360784" a="1.000000" />:
        <voxel x="-11" y="4" z="3" r="0.345098" g="0.341176" b="0.360784" a="1.000000" />C
        <voxel x="-10" y="4" z="3" r="0.345098" g="0.341176" b="0.360784" a="1.000000" />,
        <voxel x="-24" y="5" z="3" r="0.345098" g="0.341176" b="0.360784" a="1.000000" />O
        <voxel x="-23" y="5" z="3" r="0.345098" g="0.341176" b="0.360784" a="1.000000" />N
        <voxel x="-20" y="5" z="3" r="0.768627" g="0.611765" b="0.505882" a="1.000000" />L
        <voxel x="-19" y="5" z="3" r="0.290196" g="0.290196" b="0.290196" a="1.000000" />Y
    </voxels>G
    <skeleton />F
    <skeletonVoxelBindings>:
        <group constraintIndex="0">C
            <voxel index="0" />,
            <voxel index="1" />O
            <voxel index="2" />N
            <voxel index="3" />L
            <voxel index="4" />Y
            <voxel index="5" />G
            <voxel index="6" />F
            <voxel index="7" />:
            <voxel index="8" />C
            <voxel index="9" />,
            <voxel index="10" />O
            <voxel index="11" />N
            <voxel index="12" />L
            <voxel index="13" />Y
            <voxel index="14" />G
            <voxel index="15" />F
            <voxel index="16" />:
            <voxel index="17" />C
            <voxel index="18" />,
            <voxel index="19" />O
            <voxel index="20" />N
            <voxel index="21" />L
            <voxel index="22" />Y
            <voxel index="23" />G
            <voxel index="24" />F
            <voxel index="25" />:
            <voxel index="26" />C
            <voxel index="27" />,
            <voxel index="28" />O
            <voxel index="29" />N
            <voxel index="30" />L
            <voxel index="31" />Y
            <voxel index="32" />G
            <voxel index="33" />F
            <voxel index="34" />:
            <voxel index="35" />C
            <voxel index="36" />,
            <voxel index="37" />O
            <voxel index="38" />N
            <voxel index="39" />L
            <voxel index="40" />Y
            <voxel index="41" />G
            <voxel index="42" />F
            <voxel index="43" />:
            <voxel index="44" />C
            <voxel index="45" />,
            <voxel index="46" />O
            <voxel index="47" />N
            <voxel index="48" />L
            <voxel index="49" />Y
            <voxel index="50" />G
            <voxel index="51" />F
            <voxel index="52" />:
            <voxel index="53" />C
            <voxel index="54" />,
            <voxel index="55" />O
            <voxel index="56" />N
            <voxel index="57" />L
            <voxel index="58" />Y
            <voxel index="59" />G
            <voxel index="60" />F
            <voxel index="61" />:
            <voxel index="62" />C
            <voxel index="63" />,
            <voxel index="64" />O
            <voxel index="65" />N
            <voxel index="66" />L
            <voxel index="67" />Y
            <voxel index="68" />G
            <voxel index="69" />F
            <voxel index="70" />:
            <voxel index="71" />C
            <voxel index="72" />,
            <voxel index="73" />O
            <voxel index="74" />N
            <voxel index="75" />L
            <voxel index="76" />Y
            <voxel index="77" />G
            <voxel index="78" />F
            <voxel index="79" />:
            <voxel index="80" />C
            <voxel index="81" />,
            <voxel index="82" />O
            <voxel index="83" />N
            <voxel index="84" />L
            <voxel index="85" />Y
            <voxel index="86" />G
            <voxel index="87" />F
            <voxel index="88" />:
            <voxel index="89" />C
            <voxel index="90" />,
            <voxel index="91" />O
            <voxel index="92" />N
            <voxel index="93" />L
            <voxel index="94" />Y
            <voxel index="95" />G
            <voxel index="96" />F
            <voxel index="97" />:
            <voxel index="98" />C
            <voxel index="99" />,
            <voxel index="100" />O
            <voxel index="101" />N
            <voxel index="102" />L
            <voxel index="103" />Y
            <voxel index="104" />G
            <voxel index="105" />F
            <voxel index="106" />:
            <voxel index="107" />C
            <voxel index="108" />,
            <voxel index="109" />O
            <voxel index="110" />N
            <voxel index="111" />L
            <voxel index="112" />Y
            <voxel index="113" />G
            <voxel index="114" />F
            <voxel index="115" />:
            <voxel index="116" />C
            <voxel index="117" />,
            <voxel index="118" />O
            <voxel index="119" />N
            <voxel index="120" />L
            <voxel index="121" />Y
            <voxel index="122" />G
            <voxel index="123" />F
            <voxel index="124" />:
            <voxel index="125" />C
            <voxel index="126" />,
            <voxel index="127" />O
            <voxel index="128" />N
            <voxel index="129" />L
            <voxel index="130" />Y
            <voxel index="131" />G
            <voxel index="132" />F
            <voxel index="133" />:
            <voxel index="134" />C
            <voxel index="135" />,
            <voxel index="136" />O
            <voxel index="137" />N
            <voxel index="138" />L
            <voxel index="139" />Y
            <voxel index="140" />G
            <voxel index="141" />F
            <voxel index="142" />:
            <voxel index="143" />C
            <voxel index="144" />,
            <voxel index="145" />O
            <voxel index="146" />N
            <voxel index="147" />L
            <voxel index="148" />Y
            <voxel index="149" />G
            <voxel index="150" />F
            <voxel index="151" />:
            <voxel index="152" />C
            <voxel index="153" />,
            <voxel index="154" />O
            <voxel index="155" />N
            <voxel index="156" />L
            <voxel index="157" />Y
            <voxel index="158" />G
            <voxel index="159" />F
            <voxel index="160" />:
            <voxel index="161" />C
            <voxel index="162" />,
            <voxel index="163" />O
            <voxel index="164" />N
            <voxel index="165" />L
            <voxel index="166" />Y
            <voxel index="167" />G
            <voxel index="168" />F
            <voxel index="169" />:
            <voxel index="170" />C
            <voxel index="171" />,
            <voxel index="172" />O
            <voxel index="173" />N
            <voxel index="174" />L
            <voxel index="175" />Y
            <voxel index="176" />G
            <voxel index="177" />F
            <voxel index="178" />:
            <voxel index="179" />C
            <voxel index="180" />,
            <voxel index="181" />O
            <voxel index="182" />N
            <voxel index="183" />L
            <voxel index="184" />Y
            <voxel index="185" />G
            <voxel index="186" />F
            <voxel index="187" />:
            <voxel index="188" />C
            <voxel index="189" />,
            <voxel index="190" />O
            <voxel index="191" />N
            <voxel index="192" />L
            <voxel index="193" />Y
            <voxel index="194" />G
            <voxel index="195" />F
        </group>:
    </skeletonVoxelBindings>C
</model>,
